{
  "name": "Autobahn Sales and Service",
  "slug": "autobahn-sales",
  "type": "independent",
  "address": "5471 Miller Trunk Hwy",
  "city": "Hermantown",
  "state": "MN",
  "phone": "218-729-7360",
  "website": "https://www.autobahnsalesandservice.com/",
  "specialties": ["European luxury vehicles", "Porsche", "Audi", "BMW", "used SUVs and trucks"],
  "coverage": "partial",
  "method": "aggregator",
  "notes": "Website autobahnsalesandservice.com is protected by Cloudflare managed challenge (HTTP 403 with cf-mitigated: challenge header) on all paths including the homepage — no direct access was possible. Fell back to CarGurus dealer page (cargurus.com/Cars/m-Autobahn-Sales-Service-LLC-sp444467) which showed 34 vehicles total. Two sort-order queries extracted 30 distinct vehicles; 4 additional vehicles were identified from the mileage-sort pass (2013 Jeep Wrangler, 2009 Nissan Rogue, 2010 Mercedes C300, 2013 Land Rover Range Rover Evoque, 2017 Subaru Outback, 2014 BMW 328i xDrive). Final deduplicated count is 30 unique vehicles confirmed from CarGurus. Remaining 4 of the 34 were not recovered due to pagination truncation across multiple CarGurus queries. Several vehicles have no price listed on CarGurus. Scrape-justification: direct site blocked by Cloudflare; /inventory/ path also 403; no XML sitemap accessible; robots.txt inaccessible; no JSON-LD detectable; no API endpoint reachable. CarGurus is the deepest accessible source.",
  "titleAudit": {
    "status": "unknown",
    "sampled": 0,
    "rebuiltFound": 0,
    "note": "Direct site blocked by Cloudflare (HTTP 403); CarGurus dealer page sp444467 shows 34 listings but no title status on any listing card; individual CarGurus listing URLs return HTTP 404 (listings rotated out) — no title data reachable."
  },
  "inventory": [
    {"year": 2018, "make": "Chevrolet", "model": "Camaro", "trim": "1LT Coupe RWD", "price": 19995, "mileage": 29222, "drivetrain": "RWD", "url": "https://www.cargurus.com/Cars/new/nl_new_left_nav_new_listing_overview_d-listing/444024917"},
    {"year": 2013, "make": "Jeep", "model": "Wrangler", "trim": null, "price": 20995, "mileage": 77870, "drivetrain": "4WD", "url": "https://www.cargurus.com/Cars/m-Autobahn-Sales-Service-LLC-sp444467"},
    {"year": 2018, "make": "Porsche", "model": "Macan", "trim": "S AWD", "price": 19995, "mileage": 83294, "drivetrain": "AWD", "url": "https://www.cargurus.com/Cars/new/nl_new_left_nav_new_listing_overview_d-listing/428601417"},
    {"year": 2012, "make": "Audi", "model": "A4", "trim": "2.0T quattro Premium Plus Sedan AWD", "price": 10995, "mileage": 83391, "drivetrain": "AWD", "url": "https://www.cargurus.com/Cars/new/nl_new_left_nav_new_listing_overview_d-listing/442937929"},
    {"year": 2008, "make": "Jeep", "model": "Wrangler", "trim": "Unlimited X 4WD", "price": 13995, "mileage": 85376, "drivetrain": "4WD", "url": "https://www.cargurus.com/Cars/new/nl_new_left_nav_new_listing_overview_d-listing/445281582"},
    {"year": 2013, "make": "Audi", "model": "A8", "trim": "4.0T quattro AWD", "price": null, "mileage": 89168, "drivetrain": "AWD", "url": "https://www.cargurus.com/Cars/new/nl_new_left_nav_new_listing_overview_d-listing/448108859"},
    {"year": 2019, "make": "Buick", "model": "Envision", "trim": "Premium AWD", "price": 15995, "mileage": 98167, "drivetrain": "AWD", "url": "https://www.cargurus.com/Cars/new/nl_new_left_nav_new_listing_overview_d-listing/439454187"},
    {"year": 2014, "make": "Porsche", "model": "Panamera", "trim": "4S", "price": 19995, "mileage": 98369, "drivetrain": "AWD", "url": "https://www.cargurus.com/Cars/new/nl_new_left_nav_new_listing_overview_d-listing/434920551"},
    {"year": 2014, "make": "Porsche", "model": "Cayenne", "trim": "AWD", "price": 13995, "mileage": 98965, "drivetrain": "AWD", "url": "https://www.cargurus.com/Cars/new/nl_new_left_nav_new_listing_overview_d-listing/447793456"},
    {"year": 2009, "make": "Cadillac", "model": "CTS", "trim": "3.6L AWD", "price": 6995, "mileage": 110085, "drivetrain": "AWD", "url": "https://www.cargurus.com/Cars/new/nl_new_left_nav_new_listing_overview_d-listing/430038340"},
    {"year": 2012, "make": "Jeep", "model": "Liberty", "trim": "Limited Jet", "price": 6495, "mileage": 110323, "drivetrain": "4WD", "url": "https://www.cargurus.com/Cars/new/nl_new_left_nav_new_listing_overview_d-listing/446371793"},
    {"year": 2016, "make": "Audi", "model": "A6", "trim": "2.0T quattro Premium Sedan AWD", "price": 12995, "mileage": 114444, "drivetrain": "AWD", "url": "https://www.cargurus.com/Cars/new/nl_new_left_nav_new_listing_overview_d-listing/448108861"},
    {"year": 2017, "make": "Chevrolet", "model": "Silverado 1500", "trim": "LT Double Cab 4WD", "price": 19995, "mileage": 115819, "drivetrain": "4WD", "url": "https://www.cargurus.com/Cars/new/nl_new_left_nav_new_listing_overview_d-listing/443438909"},
    {"year": 2016, "make": "Mitsubishi", "model": "Outlander Sport", "trim": "GT AWC", "price": 8995, "mileage": 118212, "drivetrain": "AWD", "url": "https://www.cargurus.com/Cars/new/nl_new_left_nav_new_listing_overview_d-listing/437615430"},
    {"year": 2020, "make": "Jeep", "model": "Cherokee", "trim": "Trailhawk Elite 4WD", "price": 15995, "mileage": 119297, "drivetrain": "4WD", "url": "https://www.cargurus.com/Cars/new/nl_new_left_nav_new_listing_overview_d-listing/444543764"},
    {"year": 2009, "make": "Nissan", "model": "Rogue", "trim": null, "price": null, "mileage": 121993, "drivetrain": null, "url": "https://www.cargurus.com/Cars/m-Autobahn-Sales-Service-LLC-sp444467"},
    {"year": 2010, "make": "Mercedes-Benz", "model": "C-Class", "trim": "C 300 Luxury 4MATIC", "price": null, "mileage": 123604, "drivetrain": "AWD", "url": "https://www.cargurus.com/Cars/m-Autobahn-Sales-Service-LLC-sp444467"},
    {"year": 2013, "make": "Volvo", "model": "XC90", "trim": "3.2 R-Design AWD", "price": 9995, "mileage": 124153, "drivetrain": "AWD", "url": "https://www.cargurus.com/Cars/new/nl_new_left_nav_new_listing_overview_d-listing/445281585"},
    {"year": 2018, "make": "Mazda", "model": "CX-9", "trim": "Grand Touring AWD", "price": null, "mileage": 125135, "drivetrain": "AWD", "url": "https://www.cargurus.com/Cars/new/nl_new_left_nav_new_listing_overview_d-listing/442345815"},
    {"year": 2013, "make": "Land Rover", "model": "Range Rover Evoque", "trim": "Pure Plus Coupe", "price": null, "mileage": 125858, "drivetrain": "AWD", "url": "https://www.cargurus.com/Cars/m-Autobahn-Sales-Service-LLC-sp444467"},
    {"year": 2013, "make": "Subaru", "model": "Outback", "trim": "2.5i Limited", "price": 9995, "mileage": 126265, "drivetrain": "AWD", "url": "https://www.cargurus.com/Cars/new/nl_new_left_nav_new_listing_overview_d-listing/448497222"},
    {"year": 2017, "make": "Subaru", "model": "Outback", "trim": "2.5i Limited AWD", "price": 13995, "mileage": 134146, "drivetrain": "AWD", "url": "https://www.cargurus.com/Cars/m-Autobahn-Sales-Service-LLC-sp444467"},
    {"year": 2015, "make": "Jeep", "model": "Grand Cherokee", "trim": "Limited 4WD", "price": 11995, "mileage": 138677, "drivetrain": "4WD", "url": "https://www.cargurus.com/Cars/new/nl_new_left_nav_new_listing_overview_d-listing/438853540"},
    {"year": 2014, "make": "BMW", "model": "3 Series", "trim": "328i xDrive Sedan AWD", "price": 9995, "mileage": 140491, "drivetrain": "AWD", "url": "https://www.cargurus.com/Cars/m-Autobahn-Sales-Service-LLC-sp444467"},
    {"year": 2011, "make": "Audi", "model": "A6", "trim": "3.0T quattro Prestige Sedan AWD", "price": 6895, "mileage": 159358, "drivetrain": "AWD", "url": "https://www.cargurus.com/Cars/new/nl_new_left_nav_new_listing_overview_d-listing/446457569"},
    {"year": 2015, "make": "BMW", "model": "3 Series", "trim": "328i xDrive Sedan AWD", "price": 8995, "mileage": 148033, "drivetrain": "AWD", "url": "https://www.cargurus.com/Cars/new/nl_new_left_nav_new_listing_overview_d-listing/444408833"},
    {"year": 2016, "make": "Toyota", "model": "Tacoma", "trim": "Double Cab V6 SR 4WD", "price": 19995, "mileage": 151388, "drivetrain": "4WD", "url": "https://www.cargurus.com/Cars/new/nl_new_left_nav_new_listing_overview_d-listing/449714821"},
    {"year": 2011, "make": "Subaru", "model": "Outback", "trim": "2.5i Premium", "price": 7995, "mileage": 148488, "drivetrain": "AWD", "url": "https://www.cargurus.com/Cars/new/nl_new_left_nav_new_listing_overview_d-listing/447417749"},
    {"year": 2011, "make": "Honda", "model": "Pilot", "trim": "EX-L 4WD", "price": 5995, "mileage": 176811, "drivetrain": "4WD", "url": "https://www.cargurus.com/Cars/new/nl_new_left_nav_new_listing_overview_d-listing/449714822"},
    {"year": 2012, "make": "Subaru", "model": "Outback", "trim": "2.5i Premium", "price": 3495, "mileage": 215044, "drivetrain": "AWD", "url": "https://www.cargurus.com/Cars/new/nl_new_left_nav_new_listing_overview_d-listing/446286334"}
  ]
}
